Workbook

Sheet Sheet1_Questions
A1: 📊 TechMart Distributors – Data Analytics Practice Workbook
A2: Topics: Data Types · Validation · Duplicates · Conditional Formatting · Sorting & Filtering · Functions · Lookup · Logic
A3: Dataset lives in Sheet2_RawData (312 rows, Jan–Dec 2024). You are the analyst. Don't just use formulas — think like a problem solver.
A6: SECTION 1: Data Cleaning & Validation
A7: Identify problems in raw data before any analysis. A clean dataset is the foundation of every business decision.
A8: # | B8: Question | C8: Skill Tag | D8: Difficulty | E8: Your Answer | F8: Formula / Steps Used | G8: Business Insight (write 1 sentence) | H8: Self-Check ✓ | I8: Notes | J8: Notes
A9: 1 | B9: Open Sheet2_RawData. Scan the 'Sales Rep' column — some cells are blank. Using a COUNTBLANK function, find exactly how many sales rep entries are missing. Then, as a business analyst, explain: should these orders be assigned to a default rep or excluded from performance reports? | C9: COUNTBLANK, Data Audit | D9: Intermediate | E9: =COUNTBLANK(Sheet2_RawData!$D$2:$D$313) -> 0 | H9: ☐
A10: 2 | B10: The 'Unit Price' column has a cell with the text 'N/A' instead of a number. Use ISNUMBER + IF to flag all rows where Unit Price is not a valid number. How many such rows exist? What risk does this create if you run a SUM formula on the whole column? | C10: ISNUMBER, Error Detection | D10: Intermediate | E10: =ISNUMBER(Sheet2_RawData!$I2) -> TRUE | H10: ☐
A11: 3 | B11: Remove all duplicate Order IDs from the dataset. Before deleting, use COUNTIF to count how many Order IDs appear more than once. After removing duplicates (Data → Remove Duplicates), how many rows remain? Write the exact count. | C11: COUNTIF, Remove Duplicates | D11: Intermediate | E11: =SUMPRODUCT((COUNTIF(Sheet2_RawData!$A$2:$A$313, Sheet2_RawData!$A$2:$A$313)>1)*1) -> 23 | H11: ☐
A12: 4 | B12: A new intern added orders with 'Status' values like 'delivered', 'PENDING', and 'cancelled' — inconsistent capitalisation. Use Data Validation to create a dropdown list for the Status column allowing only: Delivered, Pending, Cancelled, Returned, Processing. How does this prevent future data quality issues? | C12: Data Validation, Data Types | D12: Intermediate | H12: ☐
A13: 5 | B13: Use conditional formatting to highlight all rows where Discount > 15% in orange. Now count how many orders received more than 15% discount using COUNTIF. What percentage of total orders is this? Is a discount rate above 15% sustainable from a business perspective? | C13: Conditional Formatting, COUNTIF | D13: Intermediate | E13: =COUNTIF(Sheet2_RawData!J2:J313,">0.15") -> 36 | H13: ☐
A14: 6 | B14: Apply conditional formatting with a colour scale on the 'Quantity' column from green (low) to red (high). What does the visual pattern tell you about typical order sizes? Which region or category tends to have the largest order volumes? (Use Sort & Filter to validate your visual observation.) | C14: Conditional Formatting, Sorting | D14: Advanced | H14: ☐
A15: 7 | B15: Create a helper column called 'Revenue (₹)' that calculates: Quantity × Unit Price × (1 – Discount). Make sure the formula handles the text error in Unit Price gracefully using IFERROR. What is the total revenue across all valid rows? | C15: IFERROR, Formula Construction | D15: Intermediate | E15: =SUM(Sheet2_RawData!M1:M313) -> 18013167 | H15: ☐
A16: 8 | B16: Sort the entire dataset by Region (A→Z), then by Category (A→Z), then by Revenue descending. What is the top-selling product in the East region? Write the product name and its revenue. | C16: Sorting, Multi-level Sort | D16: Intermediate | E16: =Sheet2_RawData!M13 -> 124989.63 | H16: ☐
A17: 9 | B17: Use AutoFilter to show only 'Cancelled' and 'Returned' orders. Calculate the total lost revenue (use the Revenue helper column if built). Which Sales Rep has the most cancellations? This is a critical business KPI — what action would you recommend? | C17: Filter, Business Analysis | D17: Advanced | E17: =SUM(Sheet2_RawData!M2:M309) -> 17712739 | F17: \ | H17: ☐
A18: 10 | B18: Use a filter to find all orders placed in Q3 2024 (July–September). Then, within Q3, find the top 5 customers by total order value. Hint: use MONTH() and YEAR() as helper columns to isolate Q3 rows. | C18: MONTH, YEAR, Filter, Sorting | D18: Advanced | H18: ☐
A20: SECTION 2: Counting & Statistical Functions
A21: Measure performance, spot outliers, and summarise data the way a business analyst would present to management.
A22: # | B22: Question | C22: Skill Tag | D22: Difficulty | E22: Your Answer | F22: Formula / Steps Used | G22: Business Insight (write 1 sentence) | H22: Self-Check ✓ | I22: Notes | J22: Notes
A23: 11 | B23: Use COUNTA to count the total number of non-empty rows in the 'Order ID' column. Then use COUNT to count only numeric values in the 'Quantity' column. Why might these two numbers differ, and what does that tell you about data quality? | C23: COUNTA, COUNT, Data Quality | D23: Intermediate | H23: ☐
A24: 12 | B24: Use COUNTIF to find: (a) how many orders are from the 'North' region, (b) how many orders have the product 'Laptop', (c) how many orders have a Discount of exactly 0%. Present these three results in a small summary table beside the data. | C24: COUNTIF, Summary Table | D24: Intermediate | H24: ☐
A25: 13 | B25: Use COUNTIFS to find orders that are BOTH from the 'Electronics' category AND have 'Delivered' status AND have a Quantity > 20. This is a multi-condition count — describe why COUNTIFS is more powerful than running three separate filters. | C25: COUNTIFS, Multi-criteria | D25: Advanced | H25: ☐
A26: 14 | B26: Calculate the AVERAGE, MEDIAN, and MODE of the 'Unit Price' column. If the average is much higher than the median, what does that suggest about the price distribution? What business decision could you make based on this insight? | C26: AVERAGE, MEDIAN, MODE | D26: Intermediate | H26: ☐
A27: 15 | B27: Use AVERAGEIF to find the average unit price for each Category separately. Which category has the highest average price? Which has the lowest? Present this as a 5-row summary table. | C27: AVERAGEIF, Category Analysis | D27: Intermediate | H27: ☐
A28: 16 | B28: Use AVERAGEIFS to find the average revenue per order for: Female-region = 'South' AND Status = 'Delivered'. Then compare it with the overall average revenue. Is the South region performing above or below average for successful deliveries? | C28: AVERAGEIFS, Regional KPI | D28: Advanced | H28: ☐
A29: 17 | B29: Find the MAX and MIN values in the 'Quantity' column. Then use LARGE(range,2) and SMALL(range,2) to find the 2nd largest and 2nd smallest order quantities. Why is LARGE/SMALL more flexible than MAX/MIN for business reporting? | C29: MAX, MIN, LARGE, SMALL | D29: Intermediate | H29: ☐
A30: 18 | B30: Create a frequency distribution: count how many orders fall into these Quantity buckets — [1–10], [11–20], [21–30], [31–40], [41–50]. Use COUNTIFS for each bucket. Which bucket has the most orders? What does this tell the warehouse team about typical shipment sizes? | C30: COUNTIFS, Distribution Analysis | D30: Advanced | H30: ☐
A31: 19 | B31: Use SUMIF to calculate total revenue for each Region. Then calculate each region's % share of total revenue using absolute references ($). Which region contributes the most? Format the % column with one decimal place. | C31: SUMIF, Absolute Reference, % Share | D31: Advanced | H31: ☐
A32: 20 | B32: Use SUMIFS to find total revenue where: Category = 'Industrial Tools' AND Status = 'Delivered' AND Discount = 0%. This is the 'clean revenue' from Industrial Tools. Compare this to total Industrial Tools revenue. What % of revenue is discounted? | C32: SUMIFS, Business Margin Analysis | D32: Expert | H32: ☐
A34: SECTION 3: Logical Functions & Conditional Intelligence
A35: Build smart classifications, flag risk, and automate decisions — the core of any analytical model.
A36: # | B36: Question | C36: Skill Tag | D36: Difficulty | E36: Your Answer | F36: Formula / Steps Used | G36: Business Insight (write 1 sentence) | H36: Self-Check ✓ | I36: Notes | J36: Notes
A37: 21 | B37: Add a column 'Order Size' using IF: if Quantity ≥ 30 label it 'Large', else if Quantity ≥ 15 label it 'Medium', else 'Small'. Use nested IFs. Count how many orders fall into each category using COUNTIF. | C37: Nested IF, Classification | D37: Intermediate | H37: ☐
A38: 22 | B38: Create a 'Risk Flag' column using IF + AND: flag as 'HIGH RISK' if Status = 'Cancelled' AND Discount > 10%, otherwise 'OK'. How many high-risk orders exist? What is the total revenue value at risk? | C38: IF, AND, Risk Flagging | D38: Intermediate | H38: ☐
A39: 23 | B39: Build a 'Bonus Eligible' column using IF + OR: a sales rep is bonus-eligible for an order if: Status = 'Delivered' OR (Status = 'Pending' AND Discount = 0%). Count bonus-eligible orders per Sales Rep using COUNTIF. | C39: IF, OR, Incentive Modelling | D39: Advanced | H39: ☐
A40: 24 | B40: Use IFS (not nested IF) to create a 'Discount Category' column: 0% → 'No Discount', 1–10% → 'Low', 11–20% → 'Medium', >20% → 'High'. Rewrite the same logic using nested IF. Which approach is more readable and why does readability matter in a business setting? | C40: IFS, Nested IF, Readability | D40: Advanced | H40: ☐
A41: 25 | B41: Add a 'Performance Score' column using this rule: IF Delivered AND No Discount → 3 points; IF Delivered AND Discount ≤ 10% → 2 points; IF Delivered AND Discount > 10% → 1 point; All other statuses → 0 points. Sum the total score per Sales Rep. Who is the top performer? | C41: IF, AND, Performance Scoring | D41: Expert | H41: ☐
A42: 26 | B42: Use NOT to find all orders that are NOT from the 'North' or 'South' region. Combine NOT with OR inside an IF to add a 'Central/East/West' flag column. Count these orders and calculate their total revenue. | C42: NOT, OR, IF, Revenue Analysis | D42: Advanced | H42: ☐
A43: 27 | B43: Create a 'Delivery Alert' column: mark 'REVIEW' if Status = 'Pending' AND Order Date is more than 90 days ago from today (use TODAY()). Mark 'OVERDUE' if more than 180 days. All others = 'OK'. How many orders are overdue? | C43: IF, AND, TODAY, Date Logic | D43: Advanced | H43: ☐
A44: 28 | B44: Use IFERROR to build a safe 'Avg Price Check' column: divide Unit Price by Quantity — but use IFERROR to return 'Data Error' instead of crashing when a non-numeric value is encountered. Why is IFERROR essential in production dashboards? | C44: IFERROR, Error Handling | D44: Intermediate | H44: ☐
A45: 29 | B45: Combine IF + COUNTIF to add a 'Duplicate Flag' column: if the Order ID appears more than once in the column, write 'DUPLICATE', else 'UNIQUE'. Verify this matches what Remove Duplicates found earlier. What are the dangers of double-counting in revenue reports? | C45: IF, COUNTIF, Duplicate Detection | D45: Advanced | H45: ☐
A46: 30 | B46: Create a 'Revenue Band' column using nested IFs on your Revenue column: < ₹5,000 → 'Micro'; ₹5,000–₹25,000 → 'Small'; ₹25,001–₹1,00,000 → 'Medium'; > ₹1,00,000 → 'Large'. Use COUNTIF to find the distribution. Present findings as if you were briefing a sales director. | C46: Nested IF, Revenue Segmentation, Communication | D46: Expert | H46: ☐
A48: SECTION 4: Lookup Functions & Cross-referencing
A49: Connect data across tables — the backbone of every business intelligence system.
A50: # | B50: Question | C50: Skill Tag | D50: Difficulty | E50: Your Answer | F50: Formula / Steps Used | G50: Business Insight (write 1 sentence) | H50: Self-Check ✓ | I50: Notes | J50: Notes
A51: 31 | B51: Build a small 'Region Lookup Table' in a new area of the sheet with columns: Region | Target Revenue (₹) — assign targets: North 5L, South 4L, East 6L, West 3.5L, Central 4.5L. Use VLOOKUP to pull the target revenue for each order's region into a new column in the main table. | C51: VLOOKUP, Reference Table | D51: Intermediate | H51: ☐
A52: 32 | B52: Using the same lookup table, calculate a 'Target Gap' column = Actual Revenue – Target (pulled via VLOOKUP). Highlight rows where actual revenue exceeds target in green using conditional formatting. Which region consistently beats its target? | C52: VLOOKUP, Conditional Formatting, KPI | D52: Advanced | H52: ☐
A53: 33 | B53: Create a Category Pricing Table: Category | Standard Unit Price. Use VLOOKUP with approximate match (TRUE) to classify whether each order's actual unit price is above or below the standard price. Flag 'Above Standard' or 'Below Standard'. | C53: VLOOKUP Approximate Match, Pricing Analysis | D53: Advanced | H53: ☐
A54: 34 | B54: Use HLOOKUP on a horizontal summary table you create: Categories as column headers, and rows for metrics like Count, Total Revenue, Avg Discount. Retrieve values dynamically using HLOOKUP. When would you choose HLOOKUP over VLOOKUP? | C54: HLOOKUP, Table Design | D54: Advanced | H54: ☐
A55: 35 | B55: Use INDEX + MATCH to find the Sales Rep who generated the single highest revenue order. INDEX+MATCH is considered superior to VLOOKUP — write a comment in the cell explaining why (hint: column order flexibility). | C55: INDEX, MATCH, Best Practices | D55: Advanced | H55: ☐
A56: 36 | B56: Use INDEX + MATCH with MATCH to do a two-way lookup: given a Region (e.g., 'East') and a Status (e.g., 'Delivered'), find the total count of orders meeting both criteria from a pivot summary table you create. This simulates a dynamic dashboard cell. | C56: INDEX, MATCH, Two-way Lookup | D56: Expert | H56: ☐
A57: 37 | B57: Build a 'Sales Rep Performance Card' using VLOOKUP / INDEX+MATCH: for any Sales Rep name entered in a cell, automatically pull — Total Orders, Total Revenue, Avg Discount, Most Common Status. Use COUNTIF, SUMIF, AVERAGEIF, and INDEX+MATCH to power this card. | C57: Multiple Lookups, Dynamic Dashboard | D57: Expert | H57: ☐
A58: 38 | B58: Use XLOOKUP (if available in your Excel version) to find the last order placed by customer 'CUST-007'. XLOOKUP can search from bottom to top — how does this differ from VLOOKUP's behaviour? If XLOOKUP isn't available, simulate it with INDEX+MATCH. | C58: XLOOKUP, Search Direction | D58: Expert | H58: ☐
A59: 39 | B59: Create a 'Product Catalogue' table with: Product | Category | Recommended Retail Price. Use VLOOKUP with IFERROR to match products from the order data — if a product doesn't exist in the catalogue, return 'Not Listed' instead of an error. This simulates a real inventory system join. | C59: VLOOKUP, IFERROR, Data Joining | D59: Advanced | H59: ☐
A60: 40 | B60: Use MATCH to find the row number of the first 'Returned' order in the dataset. Then use INDEX to extract the full row details (Order ID, Customer, Rep, Revenue) for that row. Why would a logistics manager need to quickly find the first instance of a returned order? | C60: MATCH, INDEX, Row Extraction | D60: Advanced | H60: ☐
A62: SECTION 5: Reference Types & Formula Architecture
A63: Build formulas that scale — absolute vs relative references are what separate amateur spreadsheets from professional models.
A64: # | B64: Question | C64: Skill Tag | D64: Difficulty | E64: Your Answer | F64: Formula / Steps Used | G64: Business Insight (write 1 sentence) | H64: Self-Check ✓ | I64: Notes | J64: Notes
A65: 41 | B65: In a summary table, calculate each Region's revenue as a % of Grand Total. The Grand Total cell must be an ABSOLUTE reference ($). Copy the formula across all 5 regions. What happens to the formula if you forget to lock the denominator? | C65: Absolute Reference, % Calculation | D65: Intermediate | H65: ☐
A66: 42 | B66: Build a 12-month revenue projection table. Row 1 = Jan revenue (hardcoded). Each subsequent month grows by a growth rate stored in a SINGLE cell (absolute reference). Write the formula for month 2 that you can drag to month 12 without breaking. | C66: Absolute Reference, Projection Model | D66: Advanced | H66: ☐
A67: 43 | B67: Create a multiplication table (10×10) using mixed references: the row headers are in column A, column headers in row 1. Write ONE formula for cell B2 that uses mixed references ($A2 * B$1) and can be copied to fill the entire 10×10 grid. | C67: Mixed References, Formula Efficiency | D67: Intermediate | H67: ☐
A68: 44 | B68: Use 3D referencing to write a formula on a Summary sheet that sums a value across Sheet1 and Sheet2 simultaneously. Demonstrate this concept by creating a small example — explain in the 'Business Insight' column where this is used in financial consolidation. | C68: 3D Reference, Cross-sheet Formulas | D68: Advanced | H68: ☐
A69: 45 | B69: Build a dynamic rank table: use RANK function to rank all 10 Sales Reps by total revenue. The revenue column should reference your SUMIF results. If two reps have the same revenue, how does RANK handle ties? How would you break a tie fairly? | C69: RANK, Absolute Reference, Tie-breaking | D69: Advanced | H69: ☐
A71: SECTION 6: Business Challenge Problems (Open-Ended)
A72: No step-by-step guide. Read the scenario, decide which tools to use, build the solution. Think like an analyst.
A73: # | B73: Question | C73: Skill Tag | D73: Difficulty | E73: Your Answer | F73: Formula / Steps Used | G73: Business Insight (write 1 sentence) | H73: Self-Check ✓ | I73: Notes | J73: Notes
A74: 46 | B74: SCENARIO — Sales Director Meeting: The Director asks for a one-page summary showing: Top 3 Sales Reps by revenue, Bottom 3 Regions by order count, Month with highest cancellations, and overall average discount rate. Build this using SUMIF, COUNTIF, LARGE, and AVERAGEIF. No pivot table allowed — formulas only. | C74: Multi-function, Business Reporting | D74: Expert | H74: ☐
A75: 47 | B75: SCENARIO — Customer Retention Analysis: Identify customers who have placed more than 5 orders AND have at least one 'Returned' order. These are 'At Risk' high-value customers. Use COUNTIF logic. List their IDs and total order values. What retention strategy would you recommend? | C75: COUNTIFS, Business Strategy | D75: Expert | H75: ☐
A76: 48 | B76: SCENARIO — Pricing Audit: Management suspects that large orders (Qty > 30) are being given excessive discounts (> 15%) without approval, eroding margins. Identify all such orders, calculate the revenue lost due to discount, and name the Sales Reps involved. Use SUMPRODUCT or SUMIFS. | C76: SUMPRODUCT, Margin Analysis, for sales Reps name use =Filter() function | D76: Expert | H76: ☐
A77: 49 | B77: SCENARIO — Year-End Inventory Planning: The warehouse team needs to know the top 5 products by total quantity ordered and the bottom 5 (to discontinue). Use SUMIF to aggregate quantity by product, then LARGE/SMALL or sorting to find top/bottom 5. Present findings with a recommended action for each. | C77: SUMIF, LARGE, Inventory Planning | D77: Expert | H77: ☐
A78: 50 | B78: SCENARIO — Commission Calculation Engine: Build a commission table for all 10 Sales Reps using these rules: Revenue < ₹1L → 3% commission; ₹1L–₹5L → 5%; > ₹5L → 7%. Use nested IF on SUMIF totals. Calculate the total commission payout. Which rep earns the most? Is this model fair? Suggest an improvement. | C78: Nested IF, SUMIF, Commission Model | D78: Expert | H78: ☐
A79: 51 | B79: SCENARIO — Regional Scorecard: Create a scorecard with one row per region showing: Total Revenue, Order Count, Avg Order Value, Delivered %, Cancelled %, Top Product, Top Sales Rep. Use SUMIF, COUNTIF, AVERAGEIF, COUNTIFS, and INDEX+MATCH. This is a real business dashboard — format it professionally. | C79: Full Analytics, Dashboard Design | D79: Expert | H79: ☐
A82: Remember: A formula that gives the right number but wrong insight is still a failure. Always ask — what does this number mean for the business?

Sheet Sheet2_RawData
A1: Order ID | B1: Order Date | C1: Customer ID | D1: Sales Rep | E1: Region | F1: Category | G1: Product | H1: Quantity | I1: Unit Price (₹) | J1: Discount | K1: Status | M1: Revenue | N1: year | O1: month | P1: week
A2: ORD-59823 | B2: 45343 | C2: CUST-015 | D2: =_xlfn.MODE.SNGL(D1:D288) -> 0 | E2: North | F2: Safety Equipment | G2: Vest | H2: 50 | I2: 1482.47 | J2: 0 | K2: Returned | M2: =IFERROR( Sheet2_RawData!$H113 * Sheet2_RawData!$I113 * (1 - Sheet2_RawData!$J113), "" ) -> 2561.04 | N2: =YEAR(Sheet2_RawData!$B2) -> 2024 | O2: =MONTH(Sheet2_RawData!$B2) -> 2
A3: ORD-78955 | B3: 45507 | C3: CUST-021 | D3: Neha Gupta | E3: South | F3: Electronics | G3: Keyboard | H3: 2 | I3: 912.52 | J3: 0 | K3: Delivered | M3: =IFERROR( Sheet2_RawData!$H55 * Sheet2_RawData!$I55 * (1 - Sheet2_RawData!$J55), "" ) -> 28737.504 | N3: =YEAR(Sheet2_RawData!$B3) -> 2024 | O3: =MONTH(Sheet2_RawData!$B3) -> 8 | P3: =AND($N3=2024, OR($O3=7, $O3=8, $O3=9)) -> TRUE | Q3: =SUMIFS(Sheet2_RawData!$M$3:$M$313, Sheet2_RawData!$P$3:$P$313, TRUE) -> 5733183.3
A4: ORD-25389 | B4: 45645 | C4: CUST-011 | D4: Vikram Nair | E4: West | F4: Electronics | G4: Laptop | H4: 26 | I4: 3446.06 | J4: 0.15 | K4: Cancelled | M4: =IFERROR( Sheet2_RawData!$H277 * Sheet2_RawData!$I277 * (1 - Sheet2_RawData!$J277), "" ) -> 9350.784 | N4: =YEAR(Sheet2_RawData!$B4) -> 2024 | O4: =MONTH(Sheet2_RawData!$B4) -> 12
A5: ORD-99381 | B5: 45336 | C5: CUST-009 | D5: Priya Shah | E5: South | F5: Office Supplies | G5: Stapler | H5: 5 | I5: 2287.61 | J5: 0.15 | K5: Delivered | M5: =IFERROR( Sheet2_RawData!$H152 * Sheet2_RawData!$I152 * (1 - Sheet2_RawData!$J152), "" ) -> 3689.72 | N5: =YEAR(Sheet2_RawData!$B5) -> 2024 | O5: =MONTH(Sheet2_RawData!$B5) -> 2
A6: ORD-36724 | B6: 45645 | C6: CUST-013 | D6: Priya Shah | E6: Central | F6: Furniture | G6: Desk | H6: 2 | I6: 2233.14 | J6: 0.05 | K6: Delivered | M6: =IFERROR( Sheet2_RawData!$H312 * Sheet2_RawData!$I312 * (1 - Sheet2_RawData!$J312), "" ) -> 123922.62 | N6: =YEAR(Sheet2_RawData!$B6) -> 2024 | O6: =MONTH(Sheet2_RawData!$B6) -> 12
A7: ORD-57472 | B7: 45513 | C7: CUST-022 | D7: Rahul Kumar | E7: North | F7: Industrial Tools | G7: Safety Gloves | H7: 1 | I7: 4255.4 | J7: 0.2 | K7: Delivered | M7: =IFERROR( Sheet2_RawData!$H173 * Sheet2_RawData!$I173 * (1 - Sheet2_RawData!$J173), "" ) -> 210818.7 | N7: =YEAR(Sheet2_RawData!$B7) -> 2024 | O7: =MONTH(Sheet2_RawData!$B7) -> 8 | P7: =AND($N7=2024, OR($O7=7, $O7=8, $O7=9)) -> TRUE
A8: ORD-50768 | B8: 45375 | C8: CUST-024 | D8: Vikram Nair | E8: West | F8: Safety Equipment | G8: Vest | H8: 11 | I8: 3049.17 | J8: 0.15 | K8: Pending | M8: =IFERROR( Sheet2_RawData!$H39 * Sheet2_RawData!$I39 * (1 - Sheet2_RawData!$J39), "" ) -> 93694.177 | N8: =YEAR(Sheet2_RawData!$B8) -> 2024 | O8: =MONTH(Sheet2_RawData!$B8) -> 3
A9: ORD-96752 | B9: 45576 | C9: CUST-030 | D9: Vikram Nair | E9: West | F9: Industrial Tools | G9: Drill Machine | H9: 19 | I9: 2143.89 | J9: 0.15 | K9: Processing | M9: =IFERROR( Sheet2_RawData!$H16 * Sheet2_RawData!$I16 * (1 - Sheet2_RawData!$J16), "" ) -> 29753.856 | N9: =YEAR(Sheet2_RawData!$B9) -> 2024 | O9: =MONTH(Sheet2_RawData!$B9) -> 10
A10: ORD-51245 | B10: 45582 | C10: CUST-003 | D10: Sneha Patel | E10: North | F10: Furniture | G10: Cabinet | H10: 21 | I10: 2035.77 | J10: 0 | K10: Delivered | M10: =IFERROR( Sheet2_RawData!$H289 * Sheet2_RawData!$I289 * (1 - Sheet2_RawData!$J289), "" ) -> 84367.98 | N10: =YEAR(Sheet2_RawData!$B10) -> 2024 | O10: =MONTH(Sheet2_RawData!$B10) -> 10
A11: ORD-70260 | B11: 45301 | C11: CUST-023 | D11: Rahul Kumar | E11: Central | F11: Safety Equipment | G11: Vest | H11: 5 | I11: 2015.5 | J11: 0.15 | K11: Delivered | M11: =IFERROR( Sheet2_RawData!$H286 * Sheet2_RawData!$I286 * (1 - Sheet2_RawData!$J286), "" ) -> 194818.38 | N11: =YEAR(Sheet2_RawData!$B11) -> 2024 | O11: =MONTH(Sheet2_RawData!$B11) -> 1
A12: ORD-43246 | B12: 45483 | C12: CUST-002 | D12: Rahul Kumar | E12: Central | F12: Safety Equipment | G12: Ear Plugs | H12: 25 | I12: 4372.99 | J12: 0 | K12: Pending | M12: =IFERROR( Sheet2_RawData!$H26 * Sheet2_RawData!$I26 * (1 - Sheet2_RawData!$J26), "" ) -> 14848.32 | N12: =YEAR(Sheet2_RawData!$B12) -> 2024 | O12: =MONTH(Sheet2_RawData!$B12) -> 7 | P12: =AND($N12=2024, OR($O12=7, $O12=8, $O12=9)) -> TRUE
A13: ORD-74038 | B13: 45500 | C13: CUST-001 | D13: Rahul Kumar | E13: East | F13: Office Supplies | G13: Binder | H13: 34 | I13: 4742.91 | J13: 0 | K13: Delivered | M13: =IFERROR( Sheet2_RawData!$H298 * Sheet2_RawData!$I298 * (1 - Sheet2_RawData!$J298), "" ) -> 124989.63 | N13: =YEAR(Sheet2_RawData!$B13) -> 2024 | O13: =MONTH(Sheet2_RawData!$B13) -> 7 | P13: =AND($N13=2024, OR($O13=7, $O13=8, $O13=9)) -> TRUE
A14: ORD-18357 | B14: 45468 | C14: CUST-001 | D14: Vikram Nair | E14: West | F14: Office Supplies | G14: Pen Set | H14: 48 | I14: 1128.61 | J14: 0 | K14: Delivered | M14: =IFERROR( Sheet2_RawData!$H257 * Sheet2_RawData!$I257 * (1 - Sheet2_RawData!$J257), "" ) -> 36965.664 | N14: =YEAR(Sheet2_RawData!$B14) -> 2024 | O14: =MONTH(Sheet2_RawData!$B14) -> 6
A15: ORD-24945 | B15: 45616 | C15: CUST-022 | D15: Vikram Nair | E15: West | F15: Safety Equipment | G15: Helmet | H15: 15 | I15: 1698.69 | J15: 0 | K15: Delivered | M15: =IFERROR( Sheet2_RawData!$H119 * Sheet2_RawData!$I119 * (1 - Sheet2_RawData!$J119), "" ) -> 23978.37 | N15: =YEAR(Sheet2_RawData!$B15) -> 2024 | O15: =MONTH(Sheet2_RawData!$B15) -> 11
A16: ORD-17592 | B16: 45414 | C16: CUST-002 | D16: Deepa Joshi | E16: East | F16: Electronics | G16: Printer | H16: 8 | I16: 4649.04 | J16: 0.2 | K16: Cancelled | M16: =IFERROR( Sheet2_RawData!$H252 * Sheet2_RawData!$I252 * (1 - Sheet2_RawData!$J252), "" ) -> 24146.256 | N16: =YEAR(Sheet2_RawData!$B16) -> 2024 | O16: =MONTH(Sheet2_RawData!$B16) -> 5
A17: ORD-71213 | B17: 45502 | C17: CUST-013 | D17: Amit Sharma | E17: West | F17: Industrial Tools | G17: Wrench Set | H17: 7 | I17: 529.81 | J17: 0.05 | K17: Delivered | M17: =IFERROR( Sheet2_RawData!$H284 * Sheet2_RawData!$I284 * (1 - Sheet2_RawData!$J284), "" ) -> 180998.5 | N17: =YEAR(Sheet2_RawData!$B17) -> 2024 | O17: =MONTH(Sheet2_RawData!$B17) -> 7 | P17: =AND($N17=2024, OR($O17=7, $O17=8, $O17=9)) -> TRUE
A18: ORD-89131 | B18: 45468 | C18: CUST-022 | D18: Sneha Patel | E18: South | F18: Office Supplies | G18: Paper Ream | H18: 7 | I18: 509.09 | J18: 0 | K18: Delivered | M18: =IFERROR( Sheet2_RawData!$H244 * Sheet2_RawData!$I244 * (1 - Sheet2_RawData!$J244), "" ) -> 2470.23 | N18: =YEAR(Sheet2_RawData!$B18) -> 2024 | O18: =MONTH(Sheet2_RawData!$B18) -> 6
A19: ORD-89905 | B19: 45322 | C19: CUST-020 | D19: Deepa Joshi | E19: West | F19: Safety Equipment | G19: Goggles | H19: 38 | I19: 4950.65 | J19: 0 | K19: Pending | M19: =IFERROR( Sheet2_RawData!$H17 * Sheet2_RawData!$I17 * (1 - Sheet2_RawData!$J17), "" ) -> 3523.2365 | N19: =YEAR(Sheet2_RawData!$B19) -> 2024 | O19: =MONTH(Sheet2_RawData!$B19) -> 1
A20: ORD-69243 | B20: 45484 | C20: CUST-032 | D20: Amit Sharma | E20: South | F20: Furniture | G20: Cabinet | H20: 10 | I20: 2908.26 | J20: 0 | K20: Pending | M20: =IFERROR( Sheet2_RawData!$H89 * Sheet2_RawData!$I89 * (1 - Sheet2_RawData!$J89), "" ) -> 121563.28 | N20: =YEAR(Sheet2_RawData!$B20) -> 2024 | O20: =MONTH(Sheet2_RawData!$B20) -> 7 | P20: =AND($N20=2024, OR($O20=7, $O20=8, $O20=9)) -> TRUE
A21: ORD-39389 | B21: 45471 | C21: CUST-006 | D21: Vikram Nair | E21: West | F21: Industrial Tools | G21: Safety Gloves | H21: 31 | I21: 145.95 | J21: 0.1 | K21: Delivered | M21: =IFERROR( Sheet2_RawData!$H192 * Sheet2_RawData!$I192 * (1 - Sheet2_RawData!$J192), "" ) -> 17082.6 | N21: =YEAR(Sheet2_RawData!$B21) -> 2024 | O21: =MONTH(Sheet2_RawData!$B21) -> 6
A22: ORD-82362 | B22: 45414 | C22: CUST-031 | D22: Priya Shah | E22: South | F22: Electronics | G22: Monitor | H22: 16 | I22: 3493.35 | J22: 0.15 | K22: Delivered | M22: =IFERROR( Sheet2_RawData!$H208 * Sheet2_RawData!$I208 * (1 - Sheet2_RawData!$J208), "" ) -> 63507.36 | N22: =YEAR(Sheet2_RawData!$B22) -> 2024 | O22: =MONTH(Sheet2_RawData!$B22) -> 5
A23: ORD-58916 | B23: 45525 | C23: CUST-015 | D23: Rohan Desai | E23: West | F23: Electronics | G23: Laptop | H23: 5 | I23: 3550.49 | J23: 0 | K23: Delivered | M23: =IFERROR( Sheet2_RawData!$H187 * Sheet2_RawData!$I187 * (1 - Sheet2_RawData!$J187), "" ) -> 93243.8 | N23: =YEAR(Sheet2_RawData!$B23) -> 2024 | O23: =MONTH(Sheet2_RawData!$B23) -> 8 | P23: =AND($N23=2024, OR($O23=7, $O23=8, $O23=9)) -> TRUE
A24: ORD-50499 | B24: 45431 | C24: CUST-039 | D24: Arjun Mehta | E24: Central | F24: Safety Equipment | G24: Ear Plugs | H24: 43 | I24: 4155.83 | J24: 0 | K24: Delivered | M24: =IFERROR( Sheet2_RawData!$H238 * Sheet2_RawData!$I238 * (1 - Sheet2_RawData!$J238), "" ) -> 3282.345 | N24: =YEAR(Sheet2_RawData!$B24) -> 2024 | O24: =MONTH(Sheet2_RawData!$B24) -> 5
A25: ORD-60965 | B25: 45511 | C25: CUST-026 | D25: Amit Sharma | E25: South | F25: Industrial Tools | G25: Wrench Set | H25: 2 | I25: 3700.07 | J25: 0 | K25: Delivered | M25: =IFERROR( Sheet2_RawData!$H272 * Sheet2_RawData!$I272 * (1 - Sheet2_RawData!$J272), "" ) -> 9350.784 | N25: =YEAR(Sheet2_RawData!$B25) -> 2024 | O25: =MONTH(Sheet2_RawData!$B25) -> 8 | P25: =AND($N25=2024, OR($O25=7, $O25=8, $O25=9)) -> TRUE
A26: ORD-83526 | B26: 45511 | C26: CUST-036 | D26: Kavya Iyer | E26: North | F26: Industrial Tools | G26: Wrench Set | H26: 24 | I26: 618.68 | J26: 0 | K26: Pending | M26: =IFERROR( Sheet2_RawData!$H141 * Sheet2_RawData!$I141 * (1 - Sheet2_RawData!$J141), "" ) -> 7028.208 | N26: =YEAR(Sheet2_RawData!$B26) -> 2024 | O26: =MONTH(Sheet2_RawData!$B26) -> 8 | P26: =AND($N26=2024, OR($O26=7, $O26=8, $O26=9)) -> TRUE
A27: ORD-94319 | B27: 45640 | C27: CUST-030 | D27: Rohan Desai | E27: East | F27: Safety Equipment | G27: Goggles | H27: 35 | I27: 1744.52 | J27: 0 | K27: Pending | M27: =IFERROR( Sheet2_RawData!$H32 * Sheet2_RawData!$I32 * (1 - Sheet2_RawData!$J32), "" ) -> 4850.973 | N27: =YEAR(Sheet2_RawData!$B27) -> 2024 | O27: =MONTH(Sheet2_RawData!$B27) -> 12
A28: ORD-97670 | B28: 45464 | C28: CUST-032 | D28: Sneha Patel | E28: Central | F28: Safety Equipment | G28: Ear Plugs | H28: 15 | I28: 1401.03 | J28: 0.05 | K28: Delivered | M28: =IFERROR( Sheet2_RawData!$H93 * Sheet2_RawData!$I93 * (1 - Sheet2_RawData!$J93), "" ) -> 27240.192 | N28: =YEAR(Sheet2_RawData!$B28) -> 2024 | O28: =MONTH(Sheet2_RawData!$B28) -> 6
A29: ORD-31842 | B29: 45510 | C29: CUST-021 | D29: Priya Shah | E29: North | F29: Office Supplies | G29: Paper Ream | H29: 43 | I29: 1513.42 | J29: 0.05 | K29: Pending | M29: =IFERROR( Sheet2_RawData!$H250 * Sheet2_RawData!$I250 * (1 - Sheet2_RawData!$J250), "" ) -> 146067.57 | N29: =YEAR(Sheet2_RawData!$B29) -> 2024 | O29: =MONTH(Sheet2_RawData!$B29) -> 8 | P29: =AND($N29=2024, OR($O29=7, $O29=8, $O29=9)) -> TRUE
A30: ORD-24534 | B30: 45512 | C30: CUST-027 | D30: Deepa Joshi | E30: Central | F30: Industrial Tools | G30: Voltage Tester | H30: 18 | I30: 1117.07 | J30: 0.1 | K30: Delivered | M30: =IFERROR( Sheet2_RawData!$H8 * Sheet2_RawData!$I8 * (1 - Sheet2_RawData!$J8), "" ) -> 28509.739 | N30: =YEAR(Sheet2_RawData!$B30) -> 2024 | O30: =MONTH(Sheet2_RawData!$B30) -> 8 | P30: =AND($N30=2024, OR($O30=7, $O30=8, $O30=9)) -> TRUE
A31: ORD-73298 | B31: 45558 | C31: CUST-010 | D31: Priya Shah | E31: North | F31: Office Supplies | G31: Stapler | H31: 23 | I31: 1593.86 | J31: 0.05 | K31: Cancelled | M31: =IFERROR( Sheet2_RawData!$H302 * Sheet2_RawData!$I302 * (1 - Sheet2_RawData!$J302), "" ) -> 14088.384 | N31: =YEAR(Sheet2_RawData!$B31) -> 2024 | O31: =MONTH(Sheet2_RawData!$B31) -> 9 | P31: =AND($N31=2024, OR($O31=7, $O31=8, $O31=9)) -> TRUE
A32: ORD-39015 | B32: 45604 | C32: CUST-015 | D32: Priya Shah | E32: East | F32: Safety Equipment | G32: Goggles | H32: 31 | I32: 173.87 | J32: 0.1 | K32: Delivered | M32: =IFERROR( Sheet2_RawData!$H217 * Sheet2_RawData!$I217 * (1 - Sheet2_RawData!$J217), "" ) -> 50920.95 | N32: =YEAR(Sheet2_RawData!$B32) -> 2024 | O32: =MONTH(Sheet2_RawData!$B32) -> 11
A33: ORD-92050 | B33: 45381 | C33: CUST-020 | D33: Amit Sharma | E33: South | F33: Furniture | G33: Meeting Table | H33: 18 | I33: 351.74 | J33: 0.1 | K33: Returned | M33: =IFERROR( Sheet2_RawData!$H144 * Sheet2_RawData!$I144 * (1 - Sheet2_RawData!$J144), "" ) -> 15310.608 | N33: =YEAR(Sheet2_RawData!$B33) -> 2024 | O33: =MONTH(Sheet2_RawData!$B33) -> 3
A34: ORD-13969 | B34: 45619 | C34: CUST-017 | D34: Neha Gupta | E34: North | F34: Electronics | G34: Laptop | H34: 42 | I34: 1093.5 | J34: 0.1 | K34: Delivered | M34: =IFERROR( Sheet2_RawData!$H194 * Sheet2_RawData!$I194 * (1 - Sheet2_RawData!$J194), "" ) -> 10836.973 | N34: =YEAR(Sheet2_RawData!$B34) -> 2024 | O34: =MONTH(Sheet2_RawData!$B34) -> 11
A35: ORD-12125 | B35: 45366 | C35: CUST-024 | D35: Sneha Patel | E35: East | F35: Electronics | G35: Scanner | H35: 21 | I35: 2098.95 | J35: 0.1 | K35: Returned | M35: =IFERROR( Sheet2_RawData!$H150 * Sheet2_RawData!$I150 * (1 - Sheet2_RawData!$J150), "" ) -> 7781.47 | N35: =YEAR(Sheet2_RawData!$B35) -> 2024 | O35: =MONTH(Sheet2_RawData!$B35) -> 3
A36: ORD-41946 | B36: 45533 | C36: CUST-033 | D36: Vikram Nair | E36: West | F36: Electronics | G36: Monitor | H36: 46 | I36: 1403.45 | J36: 0.2 | K36: Delivered | M36: =IFERROR( Sheet2_RawData!$H108 * Sheet2_RawData!$I108 * (1 - Sheet2_RawData!$J108), "" ) -> 159355.84 | N36: =YEAR(Sheet2_RawData!$B36) -> 2024 | O36: =MONTH(Sheet2_RawData!$B36) -> 8 | P36: =AND($N36=2024, OR($O36=7, $O36=8, $O36=9)) -> TRUE
A37: ORD-42780 | B37: 45509 | C37: CUST-029 | D37: Priya Shah | E37: South | F37: Office Supplies | G37: Binder | H37: 23 | I37: 4938.88 | J37: 0 | K37: Pending | M37: =IFERROR( Sheet2_RawData!$H77 * Sheet2_RawData!$I77 * (1 - Sheet2_RawData!$J77), "" ) -> 47154.63 | N37: =YEAR(Sheet2_RawData!$B37) -> 2024 | O37: =MONTH(Sheet2_RawData!$B37) -> 8 | P37: =AND($N37=2024, OR($O37=7, $O37=8, $O37=9)) -> TRUE
A38: ORD-65353 | B38: 45353 | C38: CUST-034 | D38: Sneha Patel | E38: Central | F38: Electronics | G38: Monitor | H38: 44 | I38: 2253.08 | J38: 0 | K38: Pending | M38: =IFERROR( Sheet2_RawData!$H149 * Sheet2_RawData!$I149 * (1 - Sheet2_RawData!$J149), "" ) -> 12450.915 | N38: =YEAR(Sheet2_RawData!$B38) -> 2024 | O38: =MONTH(Sheet2_RawData!$B38) -> 3
A39: ORD-15683 | B39: 45606 | C39: CUST-024 | D39: Deepa Joshi | E39: West | F39: Electronics | G39: Laptop | H39: 33 | I39: 2988.65 | J39: 0.05 | K39: Delivered | M39: =IFERROR( Sheet2_RawData!$H143 * Sheet2_RawData!$I143 * (1 - Sheet2_RawData!$J143), "" ) -> 46160.83 | N39: =YEAR(Sheet2_RawData!$B39) -> 2024 | O39: =MONTH(Sheet2_RawData!$B39) -> 11
A40: ORD-38971 | B40: 45586 | C40: CUST-015 | D40: Vikram Nair | E40: North | F40: Electronics | G40: Laptop | H40: 33 | I40: 3746.92 | J40: 0.1 | K40: Pending | M40: =IFERROR( Sheet2_RawData!$H199 * Sheet2_RawData!$I199 * (1 - Sheet2_RawData!$J199), "" ) -> 28617.57 | N40: =YEAR(Sheet2_RawData!$B40) -> 2024 | O40: =MONTH(Sheet2_RawData!$B40) -> 10
A41: ORD-40311 | B41: 45369 | C41: CUST-016 | D41: Vikram Nair | E41: North | F41: Office Supplies | G41: Stapler | H41: 18 | I41: 1712.45 | J41: 0.1 | K41: Delivered | M41: =IFERROR( Sheet2_RawData!$H109 * Sheet2_RawData!$I109 * (1 - Sheet2_RawData!$J109), "" ) -> 203754.18 | N41: =YEAR(Sheet2_RawData!$B41) -> 2024 | O41: =MONTH(Sheet2_RawData!$B41) -> 3
A42: ORD-66959 | B42: 45597 | C42: CUST-017 | D42: Priya Shah | E42: North | F42: Safety Equipment | G42: Gloves | H42: 12 | I42: 2923.92 | J42: 0 | K42: Delivered | M42: =IFERROR( Sheet2_RawData!$H270 * Sheet2_RawData!$I270 * (1 - Sheet2_RawData!$J270), "" ) -> 94654.75 | N42: =YEAR(Sheet2_RawData!$B42) -> 2024 | O42: =MONTH(Sheet2_RawData!$B42) -> 11
A43: ORD-55398 | B43: 45332 | C43: CUST-023 | D43: Amit Sharma | E43: West | F43: Safety Equipment | G43: Ear Plugs | H43: 50 | I43: 4032.85 | J43: 0 | K43: Delivered | M43: =IFERROR( Sheet2_RawData!$H276 * Sheet2_RawData!$I276 * (1 - Sheet2_RawData!$J276), "" ) -> 18136.31 | N43: =YEAR(Sheet2_RawData!$B43) -> 2024 | O43: =MONTH(Sheet2_RawData!$B43) -> 2
A44: ORD-39444 | B44: 45450 | C44: CUST-022 | D44: Neha Gupta | E44: Central | F44: Electronics | G44: Keyboard | H44: 6 | I44: 4101.2 | J44: 0.2 | K44: Delivered | M44: =IFERROR( Sheet2_RawData!$H7 * Sheet2_RawData!$I7 * (1 - Sheet2_RawData!$J7), "" ) -> 3404.32 | N44: =YEAR(Sheet2_RawData!$B44) -> 2024 | O44: =MONTH(Sheet2_RawData!$B44) -> 6
A45: ORD-91083 | B45: 45335 | C45: CUST-025 | D45: Rahul Kumar | E45: East | F45: Industrial Tools | G45: Wrench Set | H45: 28 | I45: 969.4 | J45: 0.1 | K45: Pending | M45: =IFERROR( Sheet2_RawData!$H308 * Sheet2_RawData!$I308 * (1 - Sheet2_RawData!$J308), "" ) -> 80368.48 | N45: =YEAR(Sheet2_RawData!$B45) -> 2024 | O45: =MONTH(Sheet2_RawData!$B45) -> 2
A46: ORD-28643 | B46: 45428 | C46: CUST-028 | D46: Sneha Patel | E46: Central | F46: Furniture | G46: Cabinet | H46: 8 | I46: 2745.58 | J46: 0.15 | K46: Delivered | M46: =IFERROR( Sheet2_RawData!$H267 * Sheet2_RawData!$I267 * (1 - Sheet2_RawData!$J267), "" ) -> 22735.84 | N46: =YEAR(Sheet2_RawData!$B46) -> 2024 | O46: =MONTH(Sheet2_RawData!$B46) -> 5
A47: ORD-30033 | B47: 45348 | C47: CUST-015 | D47: Kavya Iyer | E47: West | F47: Industrial Tools | G47: Cutter | H47: 9 | I47: 2572.16 | J47: 0 | K47: Cancelled | M47: =IFERROR( Sheet2_RawData!$H104 * Sheet2_RawData!$I104 * (1 - Sheet2_RawData!$J104), "" ) -> 25465.266 | N47: =YEAR(Sheet2_RawData!$B47) -> 2024 | O47: =MONTH(Sheet2_RawData!$B47) -> 2
A48: ORD-23474 | B48: 45412 | C48: CUST-023 | D48: Kavya Iyer | E48: South | F48: Safety Equipment | G48: Ear Plugs | H48: 47 | I48: 4793.21 | J48: 0.15 | K48: Cancelled | M48: =IFERROR( Sheet2_RawData!$H98 * Sheet2_RawData!$I98 * (1 - Sheet2_RawData!$J98), "" ) -> 87275.664 | N48: =YEAR(Sheet2_RawData!$B48) -> 2024 | O48: =MONTH(Sheet2_RawData!$B48) -> 4
A49: ORD-22219 | B49: 45335 | C49: CUST-010 | D49: Kavya Iyer | E49: East | F49: Industrial Tools | G49: Safety Gloves | H49: 44 | I49: 4618.78 | J49: 0 | K49: Delivered | M49: =IFERROR( Sheet2_RawData!$H305 * Sheet2_RawData!$I305 * (1 - Sheet2_RawData!$J305), "" ) -> 22177.35 | N49: =YEAR(Sheet2_RawData!$B49) -> 2024 | O49: =MONTH(Sheet2_RawData!$B49) -> 2
A50: ORD-69473 | B50: 45472 | C50: CUST-034 | D50: Rahul Kumar | E50: West | F50: Safety Equipment | G50: Gloves | H50: 23 | I50: 2156.24 | J50: 0.15 | K50: Pending | M50: =IFERROR( Sheet2_RawData!$H216 * Sheet2_RawData!$I216 * (1 - Sheet2_RawData!$J216), "" ) -> 113728.95 | N50: =YEAR(Sheet2_RawData!$B50) -> 2024 | O50: =MONTH(Sheet2_RawData!$B50) -> 6
A51: ORD-23069 | B51: 45517 | C51: CUST-033 | D51: Rohan Desai | E51: North | F51: Furniture | G51: Shelf | H51: 38 | I51: 1693.37 | J51: 0 | K51: Returned | M51: =IFERROR( Sheet2_RawData!$H200 * Sheet2_RawData!$I200 * (1 - Sheet2_RawData!$J200), "" ) | N51: =YEAR(Sheet2_RawData!$B51) -> 2024 | O51: =MONTH(Sheet2_RawData!$B51) -> 8 | P51: =AND($N51=2024, OR($O51=7, $O51=8, $O51=9)) -> TRUE
A52: ORD-24573 | B52: 45508 | C52: CUST-014 | D52: Vikram Nair | E52: North | F52: Electronics | G52: Laptop | H52: 10 | I52: 2766.58 | J52: 0.15 | K52: Pending | M52: =IFERROR( Sheet2_RawData!$H71 * Sheet2_RawData!$I71 * (1 - Sheet2_RawData!$J71), "" ) -> 16388.632 | N52: =YEAR(Sheet2_RawData!$B52) -> 2024 | O52: =MONTH(Sheet2_RawData!$B52) -> 8 | P52: =AND($N52=2024, OR($O52=7, $O52=8, $O52=9)) -> TRUE
A53: ORD-65296 | B53: 45363 | C53: CUST-022 | D53: Amit Sharma | E53: North | F53: Electronics | G53: Laptop | H53: 7 | I53: 1280.85 | J53: 0 | K53: Delivered | M53: =IFERROR( Sheet2_RawData!$H73 * Sheet2_RawData!$I73 * (1 - Sheet2_RawData!$J73), "" ) -> 84990.72 | N53: =YEAR(Sheet2_RawData!$B53) -> 2024 | O53: =MONTH(Sheet2_RawData!$B53) -> 3
A54: ORD-96761 | B54: 45518 | C54: CUST-011 | D54: Rohan Desai | E54: North | F54: Safety Equipment | G54: Helmet | H54: 49 | I54: 3108.3 | J54: 0.15 | K54: Delivered | M54: =IFERROR( Sheet2_RawData!$H129 * Sheet2_RawData!$I129 * (1 - Sheet2_RawData!$J129), "" ) -> 600.168 | N54: =YEAR(Sheet2_RawData!$B54) -> 2024 | O54: =MONTH(Sheet2_RawData!$B54) -> 8 | P54: =AND($N54=2024, OR($O54=7, $O54=8, $O54=9)) -> TRUE
A55: ORD-79827 | B55: 45469 | C55: CUST-039 | D55: Vikram Nair | E55: North | F55: Safety Equipment | G55: Vest | H55: 8 | I55: 3991.32 | J55: 0.1 | K55: Cancelled | M55: =IFERROR( Sheet2_RawData!$H186 * Sheet2_RawData!$I186 * (1 - Sheet2_RawData!$J186), "" ) -> 25002.38 | N55: =YEAR(Sheet2_RawData!$B55) -> 2024 | O55: =MONTH(Sheet2_RawData!$B55) -> 6
A56: ORD-29369 | B56: 45486 | C56: CUST-038 | D56: Arjun Mehta | E56: South | F56: Safety Equipment | G56: Ear Plugs | H56: 31 | I56: 894.03 | J56: 0.15 | K56: Pending | M56: =IFERROR( Sheet2_RawData!$H226 * Sheet2_RawData!$I226 * (1 - Sheet2_RawData!$J226), "" ) -> 164263.86 | N56: =YEAR(Sheet2_RawData!$B56) -> 2024 | O56: =MONTH(Sheet2_RawData!$B56) -> 7 | P56: =AND($N56=2024, OR($O56=7, $O56=8, $O56=9)) -> TRUE
A57: ORD-85529 | B57: 45429 | C57: CUST-037 | D57: Sneha Patel | E57: North | F57: Office Supplies | G57: Pen Set | H57: 38 | I57: 4756.39 | J57: 0.2 | K57: Pending | M57: =IFERROR( Sheet2_RawData!$H174 * Sheet2_RawData!$I174 * (1 - Sheet2_RawData!$J174), "" ) -> 1586.5 | N57: =YEAR(Sheet2_RawData!$B57) -> 2024 | O57: =MONTH(Sheet2_RawData!$B57) -> 5
A58: ORD-39581 | B58: 45608 | C58: CUST-008 | D58: Sneha Patel | E58: North | F58: Safety Equipment | G58: Gloves | H58: 36 | I58: 3834 | J58: 0.1 | K58: Pending | M58: =IFERROR( Sheet2_RawData!$H96 * Sheet2_RawData!$I96 * (1 - Sheet2_RawData!$J96), "" ) -> 6689.78 | N58: =YEAR(Sheet2_RawData!$B58) -> 2024 | O58: =MONTH(Sheet2_RawData!$B58) -> 11
A59: ORD-40671 | B59: 45521 | C59: CUST-016 | D59: Kavya Iyer | E59: West | F59: Industrial Tools | G59: Drill Machine | H59: 29 | I59: 3072.45 | J59: 0.2 | K59: Pending | M59: =IFERROR( Sheet2_RawData!$H36 * Sheet2_RawData!$I36 * (1 - Sheet2_RawData!$J36), "" ) -> 51646.96 | N59: =YEAR(Sheet2_RawData!$B59) -> 2024 | O59: =MONTH(Sheet2_RawData!$B59) -> 8 | P59: =AND($N59=2024, OR($O59=7, $O59=8, $O59=9)) -> TRUE
A60: ORD-39470 | B60: 45432 | C60: CUST-037 | D60: Priya Shah | E60: South | F60: Industrial Tools | G60: Voltage Tester | H60: 2 | I60: 3989.61 | J60: 0 | K60: Delivered | M60: =IFERROR( Sheet2_RawData!$H245 * Sheet2_RawData!$I245 * (1 - Sheet2_RawData!$J245), "" ) -> 15448 | N60: =YEAR(Sheet2_RawData!$B60) -> 2024 | O60: =MONTH(Sheet2_RawData!$B60) -> 5
A61: ORD-74942 | B61: 45647 | C61: CUST-021 | D61: Kavya Iyer | E61: West | F61: Industrial Tools | G61: Safety Gloves | H61: 43 | I61: 567.77 | J61: 0 | K61: Delivered | M61: =IFERROR( Sheet2_RawData!$H92 * Sheet2_RawData!$I92 * (1 - Sheet2_RawData!$J92), "" ) -> 50625.54 | N61: =YEAR(Sheet2_RawData!$B61) -> 2024 | O61: =MONTH(Sheet2_RawData!$B61) -> 12
A62: ORD-87831 | B62: 45545 | C62: CUST-031 | D62: Vikram Nair | E62: West | F62: Industrial Tools | G62: Safety Gloves | H62: 5 | I62: 1837.57 | J62: 0 | K62: Pending | M62: =IFERROR( Sheet2_RawData!$H281 * Sheet2_RawData!$I281 * (1 - Sheet2_RawData!$J281), "" ) -> 4826.934 | N62: =YEAR(Sheet2_RawData!$B62) -> 2024 | O62: =MONTH(Sheet2_RawData!$B62) -> 9 | P62: =AND($N62=2024, OR($O62=7, $O62=8, $O62=9)) -> TRUE
A63: ORD-72094 | B63: 45462 | C63: CUST-033 | D63: Neha Gupta | E63: South | F63: Office Supplies | G63: Notebook | H63: 26 | I63: 2525.39 | J63: 0 | K63: Delivered | M63: =IFERROR( Sheet2_RawData!$H123 * Sheet2_RawData!$I123 * (1 - Sheet2_RawData!$J123), "" ) -> 111777.75 | N63: =YEAR(Sheet2_RawData!$B63) -> 2024 | O63: =MONTH(Sheet2_RawData!$B63) -> 6
A64: ORD-48696 | B64: 45443 | C64: CUST-031 | D64: Amit Sharma | E64: South | F64: Industrial Tools | G64: Safety Gloves | H64: 7 | I64: 1224.17 | J64: 0.1 | K64: Delivered | M64: =IFERROR( Sheet2_RawData!$H159 * Sheet2_RawData!$I159 * (1 - Sheet2_RawData!$J159), "" ) -> 33741.46 | N64: =YEAR(Sheet2_RawData!$B64) -> 2024 | O64: =MONTH(Sheet2_RawData!$B64) -> 5
A65: ORD-61543 | B65: 45338 | C65: CUST-033 | D65: Deepa Joshi | E65: South | F65: Office Supplies | G65: Notebook | H65: 30 | I65: 2518.86 | J65: 0 | K65: Delivered | M65: =IFERROR( Sheet2_RawData!$H106 * Sheet2_RawData!$I106 * (1 - Sheet2_RawData!$J106), "" ) -> 30736.34 | N65: =YEAR(Sheet2_RawData!$B65) -> 2024 | O65: =MONTH(Sheet2_RawData!$B65) -> 2
A66: ORD-82529 | B66: 45319 | C66: CUST-001 | D66: Vikram Nair | E66: South | F66: Furniture | G66: Cabinet | H66: 46 | I66: 2693.97 | J66: 0 | K66: Delivered | M66: =IFERROR( Sheet2_RawData!$H156 * Sheet2_RawData!$I156 * (1 - Sheet2_RawData!$J156), "" ) -> 47111.96 | N66: =YEAR(Sheet2_RawData!$B66) -> 2024 | O66: =MONTH(Sheet2_RawData!$B66) -> 1
A67: ORD-64387 | B67: 45433 | C67: CUST-013 | D67: Amit Sharma | E67: South | F67: Industrial Tools | G67: Cutter | H67: 39 | I67: 2565.79 | J67: 0 | K67: Returned | M67: =IFERROR( Sheet2_RawData!$H9 * Sheet2_RawData!$I9 * (1 - Sheet2_RawData!$J9), "" ) -> 34623.823 | N67: =YEAR(Sheet2_RawData!$B67) -> 2024 | O67: =MONTH(Sheet2_RawData!$B67) -> 5
A68: ORD-30280 | B68: 45400 | C68: CUST-019 | D68: Arjun Mehta | E68: West | F68: Industrial Tools | G68: Safety Gloves | H68: 39 | I68: 1596.62 | J68: 0 | K68: Pending | M68: =IFERROR( Sheet2_RawData!$H259 * Sheet2_RawData!$I259 * (1 - Sheet2_RawData!$J259), "" ) -> 129941.44 | N68: =YEAR(Sheet2_RawData!$B68) -> 2024 | O68: =MONTH(Sheet2_RawData!$B68) -> 4
A69: ORD-44362 | B69: 45636 | C69: CUST-001 | D69: Amit Sharma | E69: North | F69: Safety Equipment | G69: Gloves | H69: 17 | I69: 2706.03 | J69: 0.05 | K69: Delivered | M69: =IFERROR( Sheet2_RawData!$H128 * Sheet2_RawData!$I128 * (1 - Sheet2_RawData!$J128), "" ) -> 22009.59 | N69: =YEAR(Sheet2_RawData!$B69) -> 2024 | O69: =MONTH(Sheet2_RawData!$B69) -> 12
A70: ORD-83000 | B70: 45619 | C70: CUST-016 | D70: Rahul Kumar | E70: South | F70: Electronics | G70: Printer | H70: 11 | I70: 2338.19 | J70: 0 | K70: Processing | M70: =IFERROR( Sheet2_RawData!$H287 * Sheet2_RawData!$I287 * (1 - Sheet2_RawData!$J287), "" ) -> 132924.26 | N70: =YEAR(Sheet2_RawData!$B70) -> 2024 | O70: =MONTH(Sheet2_RawData!$B70) -> 11
A71: ORD-52727 | B71: 45479 | C71: CUST-005 | D71: Vikram Nair | E71: South | F71: Electronics | G71: Monitor | H71: 37 | I71: 553.67 | J71: 0.2 | K71: Delivered | M71: =IFERROR( Sheet2_RawData!$H151 * Sheet2_RawData!$I151 * (1 - Sheet2_RawData!$J151), "" ) -> 129700.55 | N71: =YEAR(Sheet2_RawData!$B71) -> 2024 | O71: =MONTH(Sheet2_RawData!$B71) -> 7 | P71: =AND($N71=2024, OR($O71=7, $O71=8, $O71=9)) -> TRUE
A72: ORD-65108 | B72: 45390 | C72: CUST-027 | D72: Vikram Nair | E72: Central | F72: Electronics | G72: Keyboard | H72: 21 | I72: 2041.88 | J72: 0 | K72: Pending | M72: =IFERROR( Sheet2_RawData!$H56 * Sheet2_RawData!$I56 * (1 - Sheet2_RawData!$J56), "" ) -> 23557.691 | N72: =YEAR(Sheet2_RawData!$B72) -> 2024 | O72: =MONTH(Sheet2_RawData!$B72) -> 4
A73: ORD-20357 | B73: 45495 | C73: CUST-013 | D73: Sneha Patel | E73: South | F73: Electronics | G73: Printer | H73: 40 | I73: 2655.96 | J73: 0.2 | K73: Delivered | M73: =IFERROR( Sheet2_RawData!$H191 * Sheet2_RawData!$I191 * (1 - Sheet2_RawData!$J191), "" ) -> 37204.092 | N73: =YEAR(Sheet2_RawData!$B73) -> 2024 | O73: =MONTH(Sheet2_RawData!$B73) -> 7 | P73: =AND($N73=2024, OR($O73=7, $O73=8, $O73=9)) -> TRUE
A74: ORD-17780 | B74: 45397 | C74: CUST-028 | D74: Neha Gupta | E74: East | F74: Furniture | G74: Meeting Table | H74: 11 | I74: 3099.95 | J74: 0.2 | K74: Delivered | M74: =IFERROR( Sheet2_RawData!$H220 * Sheet2_RawData!$I220 * (1 - Sheet2_RawData!$J220), "" ) -> 37129.335 | N74: =YEAR(Sheet2_RawData!$B74) -> 2024 | O74: =MONTH(Sheet2_RawData!$B74) -> 4
A75: ORD-94939 | B75: 45641 | C75: CUST-024 | D75: Rohan Desai | E75: East | F75: Office Supplies | G75: Stapler | H75: 23 | I75: 1087.06 | J75: 0 | K75: Pending | M75: =IFERROR( Sheet2_RawData!$H221 * Sheet2_RawData!$I221 * (1 - Sheet2_RawData!$J221), "" ) -> 12249.567 | N75: =YEAR(Sheet2_RawData!$B75) -> 2024 | O75: =MONTH(Sheet2_RawData!$B75) -> 12
A76: ORD-58971 | B76: 45602 | C76: CUST-015 | D76: Sneha Patel | E76: Central | F76: Office Supplies | G76: Paper Ream | H76: 9 | I76: 2417 | J76: 0.05 | K76: Pending | M76: =IFERROR( Sheet2_RawData!$H131 * Sheet2_RawData!$I131 * (1 - Sheet2_RawData!$J131), "" ) -> 6251.22 | N76: =YEAR(Sheet2_RawData!$B76) -> 2024 | O76: =MONTH(Sheet2_RawData!$B76) -> 11
A77: ORD-34267 | B77: 45645 | C77: CUST-008 | D77: Sneha Patel | E77: East | F77: Office Supplies | G77: Paper Ream | H77: 47 | I77: 1003.29 | J77: 0 | K77: Pending | M77: =IFERROR( Sheet2_RawData!$H65 * Sheet2_RawData!$I65 * (1 - Sheet2_RawData!$J65), "" ) -> 75565.8 | N77: =YEAR(Sheet2_RawData!$B77) -> 2024 | O77: =MONTH(Sheet2_RawData!$B77) -> 12
A78: ORD-39219 | B78: 45408 | C78: CUST-031 | D78: Arjun Mehta | E78: West | F78: Furniture | G78: Desk | H78: 15 | I78: 1037.89 | J78: 0.05 | K78: Delivered | M78: =IFERROR( Sheet2_RawData!$H181 * Sheet2_RawData!$I181 * (1 - Sheet2_RawData!$J181), "" ) -> 121912.56 | N78: =YEAR(Sheet2_RawData!$B78) -> 2024 | O78: =MONTH(Sheet2_RawData!$B78) -> 4
A79: ORD-78879 | B79: 45333 | C79: CUST-014 | D79: Rahul Kumar | E79: West | F79: Industrial Tools | G79: Cutter | H79: 49 | I79: 1274.95 | J79: 0.2 | K79: Pending | M79: =IFERROR( Sheet2_RawData!$H118 * Sheet2_RawData!$I118 * (1 - Sheet2_RawData!$J118), "" ) -> 62558.595 | N79: =YEAR(Sheet2_RawData!$B79) -> 2024 | O79: =MONTH(Sheet2_RawData!$B79) -> 2
A80: ORD-66346 | B80: 45399 | C80: CUST-020 | D80: Neha Gupta | E80: Central | F80: Industrial Tools | G80: Wrench Set | H80: 26 | I80: 2762.29 | J80: 0 | K80: Delivered | M80: =IFERROR( Sheet2_RawData!$H258 * Sheet2_RawData!$I258 * (1 - Sheet2_RawData!$J258), "" ) -> 8032.71 | N80: =YEAR(Sheet2_RawData!$B80) -> 2024 | O80: =MONTH(Sheet2_RawData!$B80) -> 4
A81: ORD-92578 | B81: 45306 | C81: CUST-009 | D81: Rahul Kumar | E81: East | F81: Electronics | G81: Monitor | H81: 19 | I81: 2218.67 | J81: 0.15 | K81: Delivered | M81: =IFERROR( Sheet2_RawData!$H3 * Sheet2_RawData!$I3 * (1 - Sheet2_RawData!$J3), "" ) -> 1825.04 | N81: =YEAR(Sheet2_RawData!$B81) -> 2024 | O81: =MONTH(Sheet2_RawData!$B81) -> 1
A82: ORD-57964 | B82: 45498 | C82: CUST-007 | D82: Arjun Mehta | E82: Central | F82: Industrial Tools | G82: Safety Gloves | H82: 28 | I82: 712.98 | J82: 0 | K82: Pending | M82: =IFERROR( Sheet2_RawData!$H41 * Sheet2_RawData!$I41 * (1 - Sheet2_RawData!$J41), "" ) -> 27741.69 | N82: =YEAR(Sheet2_RawData!$B82) -> 2024 | O82: =MONTH(Sheet2_RawData!$B82) -> 7 | P82: =AND($N82=2024, OR($O82=7, $O82=8, $O82=9)) -> TRUE
A83: ORD-94040 | B83: 45318 | C83: CUST-011 | D83: Amit Sharma | E83: Central | F83: Industrial Tools | G83: Cutter | H83: 13 | I83: 4016.23 | J83: 0 | K83: Returned | M83: =IFERROR( Sheet2_RawData!$H95 * Sheet2_RawData!$I95 * (1 - Sheet2_RawData!$J95), "" ) -> 156393.2 | N83: =YEAR(Sheet2_RawData!$B83) -> 2024 | O83: =MONTH(Sheet2_RawData!$B83) -> 1
A84: ORD-75612 | B84: 45426 | C84: CUST-008 | D84: Kavya Iyer | E84: East | F84: Electronics | G84: Printer | H84: 19 | I84: 2202.09 | J84: 0.05 | K84: Delivered | M84: =IFERROR( Sheet2_RawData!$H102 * Sheet2_RawData!$I102 * (1 - Sheet2_RawData!$J102), "" ) -> 12997.51 | N84: =YEAR(Sheet2_RawData!$B84) -> 2024 | O84: =MONTH(Sheet2_RawData!$B84) -> 5
A85: ORD-19835 | B85: 45321 | C85: CUST-023 | D85: Arjun Mehta | E85: West | F85: Industrial Tools | G85: Safety Gloves | H85: 40 | I85: 4990.85 | J85: 0 | K85: Pending | M85: =IFERROR( Sheet2_RawData!$H46 * Sheet2_RawData!$I46 * (1 - Sheet2_RawData!$J46), "" ) -> 18669.944 | N85: =YEAR(Sheet2_RawData!$B85) -> 2024 | O85: =MONTH(Sheet2_RawData!$B85) -> 1
A86: ORD-96761 | B86: 45518 | C86: CUST-011 | D86: Rohan Desai | E86: North | F86: Safety Equipment | G86: Helmet | H86: 49 | I86: 3108.3 | J86: 0.15 | K86: Delivered | M86: =IFERROR( Sheet2_RawData!$H206 * Sheet2_RawData!$I206 * (1 - Sheet2_RawData!$J206), "" ) -> 86854.896 | N86: =YEAR(Sheet2_RawData!$B86) -> 2024 | O86: =MONTH(Sheet2_RawData!$B86) -> 8 | P86: =AND($N86=2024, OR($O86=7, $O86=8, $O86=9)) -> TRUE
A87: ORD-63545 | B87: 45293 | C87: CUST-006 | D87: Vikram Nair | E87: South | F87: Electronics | G87: Monitor | H87: 11 | I87: 1237.33 | J87: 0.1 | K87: Delivered | M87: =IFERROR( Sheet2_RawData!$H145 * Sheet2_RawData!$I145 * (1 - Sheet2_RawData!$J145), "" ) -> 18820.13 | N87: =YEAR(Sheet2_RawData!$B87) -> 2024 | O87: =MONTH(Sheet2_RawData!$B87) -> 1
A88: ORD-14018 | B88: 45616 | C88: CUST-010 | D88: Rohan Desai | E88: North | F88: Office Supplies | G88: Paper Ream | H88: 37 | I88: 3303.86 | J88: 0 | K88: Delivered | M88: =IFERROR( Sheet2_RawData!$H165 * Sheet2_RawData!$I165 * (1 - Sheet2_RawData!$J165), "" ) -> 36132.735 | N88: =YEAR(Sheet2_RawData!$B88) -> 2024 | O88: =MONTH(Sheet2_RawData!$B88) -> 11
A89: ORD-15399 | B89: 45580 | C89: CUST-011 | D89: Rohan Desai | E89: Central | F89: Furniture | G89: Meeting Table | H89: 43 | I89: 3141.17 | J89: 0.1 | K89: Delivered | M89: =IFERROR( Sheet2_RawData!$H300 * Sheet2_RawData!$I300 * (1 - Sheet2_RawData!$J300), "" ) -> 4824.37 | N89: =YEAR(Sheet2_RawData!$B89) -> 2024 | O89: =MONTH(Sheet2_RawData!$B89) -> 10
A90: ORD-81496 | B90: 45384 | C90: CUST-006 | D90: Vikram Nair | E90: Central | F90: Industrial Tools | G90: Safety Gloves | H90: 47 | I90: 2151.27 | J90: 0.05 | K90: Pending | M90: =IFERROR( Sheet2_RawData!$H99 * Sheet2_RawData!$I99 * (1 - Sheet2_RawData!$J99), "" ) -> 45175.9 | N90: =YEAR(Sheet2_RawData!$B90) -> 2024 | O90: =MONTH(Sheet2_RawData!$B90) -> 4
A91: ORD-74764 | B91: 45613 | C91: CUST-039 | D91: Rohan Desai | E91: South | F91: Furniture | G91: Cabinet | H91: 10 | I91: 3813.07 | J91: 0.15 | K91: Delivered | M91: =IFERROR( Sheet2_RawData!$H111 * Sheet2_RawData!$I111 * (1 - Sheet2_RawData!$J111), "" ) -> 159145.82 | N91: =YEAR(Sheet2_RawData!$B91) -> 2024 | O91: =MONTH(Sheet2_RawData!$B91) -> 11
A92: ORD-47880 | B92: 45444 | C92: CUST-016 | D92: Sneha Patel | E92: West | F92: Office Supplies | G92: Binder | H92: 18 | I92: 2812.53 | J92: 0 | K92: Processing | M92: =IFERROR( Sheet2_RawData!$H282 * Sheet2_RawData!$I282 * (1 - Sheet2_RawData!$J282), "" ) -> 0 | N92: =YEAR(Sheet2_RawData!$B92) -> 2024 | O92: =MONTH(Sheet2_RawData!$B92) -> 6
A93: ORD-24530 | B93: 45324 | C93: CUST-004 | D93: Priya Shah | E93: East | F93: Office Supplies | G93: Notebook | H93: 16 | I93: 2128.14 | J93: 0.2 | K93: Pending | M93: =IFERROR( Sheet2_RawData!$H210 * Sheet2_RawData!$I210 * (1 - Sheet2_RawData!$J210), "" ) -> 88592.535 | N93: =YEAR(Sheet2_RawData!$B93) -> 2024 | O93: =MONTH(Sheet2_RawData!$B93) -> 2
A94: ORD-37767 | B94: 45511 | C94: CUST-023 | D94: Deepa Joshi | E94: North | F94: Safety Equipment | G94: Helmet | H94: 5 | I94: 3988.61 | J94: 0.05 | K94: Delivered | M94: =IFERROR( Sheet2_RawData!$H237 * Sheet2_RawData!$I237 * (1 - Sheet2_RawData!$J237), "" ) -> 21774.4 | N94: =YEAR(Sheet2_RawData!$B94) -> 2024 | O94: =MONTH(Sheet2_RawData!$B94) -> 8 | P94: =AND($N94=2024, OR($O94=7, $O94=8, $O94=9)) -> TRUE
A95: ORD-84289 | B95: 45646 | C95: CUST-007 | D95: Neha Gupta | E95: East | F95: Industrial Tools | G95: Voltage Tester | H95: 34 | I95: 4599.8 | J95: 0 | K95: Delivered | M95: =IFERROR( Sheet2_RawData!$H62 * Sheet2_RawData!$I62 * (1 - Sheet2_RawData!$J62), "" ) -> 9187.85 | N95: =YEAR(Sheet2_RawData!$B95) -> 2024 | O95: =MONTH(Sheet2_RawData!$B95) -> 12
A96: ORD-98148 | B96: 45626 | C96: CUST-038 | D96: Sneha Patel | E96: South | F96: Safety Equipment | G96: Goggles | H96: 23 | I96: 290.86 | J96: 0 | K96: Delivered | M96: =IFERROR( Sheet2_RawData!$H227 * Sheet2_RawData!$I227 * (1 - Sheet2_RawData!$J227), "" ) -> 53387.482 | N96: =YEAR(Sheet2_RawData!$B96) -> 2024 | O96: =MONTH(Sheet2_RawData!$B96) -> 11
A97: ORD-99241 | B97: 45629 | C97: CUST-013 | D97: Sneha Patel | E97: East | F97: Furniture | G97: Meeting Table | H97: 40 | I97: 1290.6 | J97: 0.2 | K97: Pending | M97: =IFERROR( Sheet2_RawData!$H268 * Sheet2_RawData!$I268 * (1 - Sheet2_RawData!$J268), "" ) -> 15141.042 | N97: =YEAR(Sheet2_RawData!$B97) -> 2024 | O97: =MONTH(Sheet2_RawData!$B97) -> 12
A98: ORD-64477 | B98: 45543 | C98: CUST-025 | D98: Sneha Patel | E98: South | F98: Electronics | G98: Scanner | H98: 36 | I98: 2551.92 | J98: 0.05 | K98: Delivered | M98: =IFERROR( Sheet2_RawData!$H60 * Sheet2_RawData!$I60 * (1 - Sheet2_RawData!$J60), "" ) -> 7979.22 | N98: =YEAR(Sheet2_RawData!$B98) -> 2024 | O98: =MONTH(Sheet2_RawData!$B98) -> 9 | P98: =AND($N98=2024, OR($O98=7, $O98=8, $O98=9)) -> TRUE
A99: ORD-27275 | B99: 45305 | C99: CUST-009 | D99: Rohan Desai | E99: East | F99: Safety Equipment | G99: Helmet | H99: 35 | I99: 1290.74 | J99: 0 | K99: Delivered | M99: =IFERROR( Sheet2_RawData!$H255 * Sheet2_RawData!$I255 * (1 - Sheet2_RawData!$J255), "" ) -> 100546.38 | N99: =YEAR(Sheet2_RawData!$B99) -> 2024 | O99: =MONTH(Sheet2_RawData!$B99) -> 1
A100: ORD-70482 | B100: 45350 | C100: CUST-036 | E100: South | F100: Safety Equipment | G100: Vest | H100: 1 | I100: 2783.64 | J100: 0 | K100: Delivered | M100: =IFERROR( Sheet2_RawData!$H292 * Sheet2_RawData!$I292 * (1 - Sheet2_RawData!$J292), "" ) -> 64628.055 | N100: =YEAR(Sheet2_RawData!$B100) -> 2024 | O100: =MONTH(Sheet2_RawData!$B100) -> 2
...
